<?xml version="1.0" encoding="utf-8"?>
<root>
    <SERVICE>
        <id>manage_entities</id>
        <name>_ENTITIES</name>
        <comment>_MANAGE_ENTITIES_DESC</comment>
        <servicepage>/administration/entities</servicepage>
        <servicetype>admin</servicetype>
        <category>organisation</category>
        <system_service>false</system_service>
        <style>fa fa-sitemap</style>
        <enabled>true</enabled>
        <WHEREAMIUSED>
            <page>admin.php</page>
            <nature>listelement</nature>
        </WHEREAMIUSED>
        <angular>true</angular>
    </SERVICE>
    <SERVICE>
        <id>admin_listmodels</id>
        <name>_LISTMODELS_WORKFLOW</name>
        <comment>_MANAGE_LISTMODELS_WORKFLOW_DESC</comment>
        <servicepage>/administration/diffusionModels</servicepage>
        <category>organisation</category>
        <servicetype>admin</servicetype>
        <system_service>false</system_service>
        <style>fa fa-th-list</style>
        <enabled>true</enabled>
        <WHEREAMIUSED>
            <page>admin.php</page>
            <nature>listelement</nature>
        </WHEREAMIUSED>
        <angular>true</angular>
    </SERVICE>
    <SERVICE>
        <id>entities_print_sep_mlb</id>
        <name>_ENTITIES_PRINT_SEP_MLB</name>
        <comment>_ENTITIES_PRINT_SEP_MLB</comment>
        <servicepage>/separators/print</servicepage>
        <servicetype>menu</servicetype>
        <system_service>false</system_service>
        <enabled>true</enabled>
        <style>fa fa-print</style>
        <angular>true</angular>
    </SERVICE>
</root>
