<?xml version="1.0" encoding="UTF-8" ?>
<ArchiveTransfer xmlns="fr:gouv:culture:archivesdefrance:seda:v2.0">
    <?merge ArchiveTransfer.comment ?><Comment><?merge .value ?></Comment>
    <Date><?merge ArchiveTransfer.date ?></Date>
    <?merge ArchiveTransfer.messageIdentifier $messageIdentifier ?><?xinclude /resources/MessageIdentifier.xml ?>
    <?merge ArchiveTransfer.archivalAgreement $archivalAgreement ?><?xinclude /resources/ArchivalAgreement.xml ?>
    <?xinclude /resources/CodeListVersions.xml ?>
    <?merge ArchiveTransfer.dataObjectPackage $dataObjectPackage ?>
    <?xinclude /resources/DataObjectPackage.xml ?>
    <ArchivalAgency>
        <?merge ArchiveTransfer.archivalAgency $organization ?>
        <?xinclude /resources/Organization.xml ?>
    </ArchivalAgency>
    <TransferringAgency>
        <?merge ArchiveTransfer.transferringAgency $organization ?>
        <?xinclude /resources/Organization.xml ?>
    </TransferringAgency>
</ArchiveTransfer>